pyworldatlas/__init__.py
pyworldatlas/atlas.py
pyworldatlas/cli.py
pyworldatlas/worldatlas.sqlite3
pyworldatlas/worldatlas.sqlite3.gz
pyworldatlas-0.0.12.dist-info/METADATA
pyworldatlas-0.0.12.dist-info/WHEEL
pyworldatlas-0.0.12.dist-info/entry_points.txt
pyworldatlas-0.0.12.dist-info/top_level.txt
pyworldatlas-0.0.12.dist-info/RECORD
