Metadata-Version: 2.1
Name: pyworldatlas
Version: 0.0.12
Summary: Comprehensive and Lightweight Country Data Package
Home-page: https://jcari-dev.github.io/pyworldatlas-documentation/
Author: jcari-dev
License: MIT
Project-URL: Documentation, https://jcari-dev.github.io/pyworldatlas-documentation/
Project-URL: Issue Tracker, https://github.com/jcari-dev/pyworldatlas-issue-tracker
Project-URL: PyPI, https://pypi.org/project/pyworldatlas/
Keywords: country data atlas global statistics geography government economy
Classifier: Development Status :: 3 - Alpha
Classifier: Intended Audience :: Developers
Classifier: License :: OSI Approved :: MIT License
Classifier: Programming Language :: Python :: 3.8
Classifier: Programming Language :: Python :: 3.9
Classifier: Programming Language :: Python :: 3.10
Classifier: Programming Language :: Python :: 3.11
Classifier: Programming Language :: Python :: 3.12
Classifier: Topic :: Software Development :: Libraries :: Python Modules
Classifier: Topic :: Utilities
Requires-Python: >=3.8, <3.13
